wappa/__init__.py
wappa/api/__init__.py
wappa/api/controllers/__init__.py
wappa/api/controllers/webhook_controller.py
wappa/api/dependencies/__init__.py
wappa/api/dependencies/cache_dependencies.py
wappa/api/dependencies/event_dependencies.py
wappa/api/dependencies/whatsapp_dependencies.py
wappa/api/dependencies/whatsapp_media_dependencies.py
wappa/api/middleware/__init__.py
wappa/api/middleware/error_handler.py
wappa/api/middleware/owner.py
wappa/api/middleware/request_logging.py
wappa/api/models/handler_models.py
wappa/api/routes/__init__.py
wappa/api/routes/health.py
wappa/api/routes/webhooks.py
wappa/api/routes/whatsapp_combined.py
wappa/api/routes/whatsapp/__init__.py
wappa/api/routes/whatsapp/whatsapp_health.py
wappa/api/routes/whatsapp/whatsapp_interactive.py
wappa/api/routes/whatsapp/whatsapp_media.py
wappa/api/routes/whatsapp/whatsapp_messages.py
wappa/api/routes/whatsapp/whatsapp_specialized.py
wappa/api/routes/whatsapp/whatsapp_state_handlers.py
wappa/api/routes/whatsapp/whatsapp_templates.py
wappa/api/services/__init__.py
wappa/api/services/handler_state_service.py
wappa/api/services/template_state_service.py
wappa/api/utils/__init__.py
wappa/api/utils/error_helpers.py
wappa/api/utils/event_decorators.py
wappa/api/utils/response_helpers.py
wappa/api/utils/tenant_helpers.py
wappa/cli/__init__.py
wappa/cli/main.py
wappa/cli/examples/db_redis_echo_example/README.md
wappa/cli/examples/db_redis_echo_example/app/__init__.py
wappa/cli/examples/db_redis_echo_example/app/main.py
wappa/cli/examples/db_redis_echo_example/app/master_event.py
wappa/cli/examples/db_redis_echo_example/app/config/__init__.py
wappa/cli/examples/db_redis_echo_example/app/config/config.py
wappa/cli/examples/db_redis_echo_example/app/handlers/__init__.py
wappa/cli/examples/db_redis_echo_example/app/handlers/command_handlers.py
wappa/cli/examples/db_redis_echo_example/app/handlers/message_handlers.py
wappa/cli/examples/db_redis_echo_example/app/models/__init__.py
wappa-0.2.15.dist-info/METADATA
wappa-0.2.15.dist-info/WHEEL
wappa-0.2.15.dist-info/entry_points.txt
wappa-0.2.15.dist-info/licenses/LICENSE
wappa-0.2.15.dist-info/RECORD
