Metadata-Version: 2.4
Name: wappa
Version: 0.2.15
Summary: Open Source Framework to develop smart Workflows, Agents and full chat applications through WhatsApp
Project-URL: Homepage, https://wappa.mimeia.com
Project-URL: Documentation, https://wappa.mimeia.com/docs
Project-URL: Repository, https://github.com/sashanclrp/wappa
Project-URL: Issues, https://github.com/sashanclrp/wappa/issues
Project-URL: Changelog, https://github.com/sashanclrp/wappa/blob/main/CHANGELOG.md
Author-email: Sasha Canal <contact@mimeia.com>
License:                                  Apache License
License-File: LICENSE
Keywords: agents,ai-agents,business-api,chatbot,messaging,webhook,whatsapp,workflows
Classifier: Development Status :: 4 - Beta
Classifier: Intended Audience :: Developers
Classifier: License :: OSI Approved :: Apache Software License
Classifier: Operating System :: OS Independent
Classifier: Programming Language :: Python :: 3
Classifier: Programming Language :: Python :: 3.12
Classifier: Topic :: Communications :: Chat
Classifier: Topic :: Internet :: WWW/HTTP :: HTTP Servers
Classifier: Topic :: Software Development :: Libraries :: Python Modules
Requires-Python: >=3.12
Requires-Dist: aiofiles>=24.1.0
Requires-Dist: aiohttp>=3.11.0
Requires-Dist: asyncpg>=0.31.0
Requires-Dist: fastapi>=0.115.0
Requires-Dist: hypercorn>=0.17.0
Requires-Dist: numpy>=2.2.0
Requires-Dist: openai>=1.69.0
Requires-Dist: opencv-python-headless>=4.11.0
Requires-Dist: pillow>=11.1.0
Requires-Dist: pydantic-settings>=2.10.0
Requires-Dist: pydantic>=2.8.0
Requires-Dist: python-dotenv>=1.0.0
Requires-Dist: python-multipart>=0.0.6
Requires-Dist: redis>=5.2.0
Requires-Dist: rich>=13.0.0
Requires-Dist: sqlmodel>=0.0.24
Requires-Dist: typer>=0.9.0
Requires-Dist: uvicorn[standard]>=0.24.0
